AUTHORS
LICENSE
MANIFEST.in
README.rst
setup.cfg
setup.py
django_geo.egg-info/PKG-INFO
django_geo.egg-info/SOURCES.txt
django_geo.egg-info/dependency_links.txt
django_geo.egg-info/requires.txt
django_geo.egg-info/top_level.txt
geo/__init__.py
geo/admin.py
geo/apps.py
geo/config.py
geo/exceptions.py
geo/forms.py
geo/hierarchy.py
geo/loaders.py
geo/models.py
geo/rest.py
geo/translation.py
geo/urls.py
geo/utils.py
geo/views.py
geo/management/__init__.py
geo/management/commands/__init__.py
geo/management/commands/dumpdata.py
geo/management/commands/geoload.py
geo/management/commands/hierarchy.py
geo/migrations/0001_initial.py
geo/migrations/0002_location_iata.py
geo/migrations/__init__.py
geo/requirements/install.pip
geo/requirements/testing.pip
geo/south_migrations/0001_initial.py
geo/south_migrations/0002_auto__add_field_country_undp__add_field_country_nato3__add_field_count.py
geo/south_migrations/0003_auto__chg_field_country_icao__chg_field_country_itu__del_unique_countr.py
geo/south_migrations/0004_auto__del_field_location__order__add_field_location_loccode__add_field.py
geo/south_migrations/0005_auto__add_field_location__order__add_unique_location_area_name.py
geo/south_migrations/0006_auto__add_field_location_iata.py
geo/south_migrations/__init__.py
geo/templates/admin/geo/change_form.html
geo/templatetags/__init__.py
geo/templatetags/geo.py
geo/templatetags/geo_admin.py
tests/__init__.py
tests/conftest.py
tests/ddf_fixture.py
tests/fixtures.py
tests/settings.py
tests/test_admin.py
tests/test_forms.py
tests/test_issues.py
tests/test_loaders.py
tests/test_models.py
tests/test_tree.py
tests/urls.py
tests/util.py