Metadata-Version: 1.1
Name: django-geo
Version: 0.8
Summary: A Django application which manage administrative geographical data.
Home-page: https://github.com/saxix/django-geo
Author: sax
Author-email: sax@os4d.org
License: BSD
Download-URL: https://github.com/saxix/django-geo/tarball/master
Platform: any
Classifier: Environment :: Web Environment
Classifier: Framework :: Django
Classifier: Operating System :: OS Independent
Classifier: Programming Language :: Python
Classifier: Intended Audience :: Developers
